<?xml version="1.0" encoding="UTF-8"?>
<qes:espresso xmlns:xsi="http://www.w3.org/2001/XMLSchema-instance" xmlns:qes="http://www.quantum-espresso.org/ns/qes/qes-1.0" xsi:schemaLocation="http://www.quantum-espresso.org/ns/qes/qes-1.0 http://www.quantum-espresso.org/ns/qes/qes_241104.xsd" Units="Hartree atomic units">
<!-- All quantities are in Hartree atomic units unless otherwise specified -->
  <general_info>
    <xml_format NAME="QEXSD" VERSION="24.11.04">QEXSD_24.11.04</xml_format>
    <creator NAME="PWSCF" VERSION="7.4.1">XML file generated by PWSCF</creator>
    <created DATE=" 9Sep2025" TIME=" 8:36:31">This run was terminated on:   8:36:31   9 Sep 2025</created>
    <job></job>
  </general_info>
  <parallel_info>
    <nprocs>1</nprocs>
    <nthreads>1</nthreads>
    <ntasks>1</ntasks>
    <nbgrp>1</nbgrp>
    <npool>1</npool>
    <ndiag>1</ndiag>
  </parallel_info>
  <input>
    <control_variables>
      <title></title>
      <calculation>scf</calculation>
      <restart_mode>from_scratch</restart_mode>
      <prefix>graphene</prefix>
      <pseudo_dir>../../../../../pseudos/</pseudo_dir>
      <outdir>./tmp/</outdir>
      <stress>false</stress>
      <forces>false</forces>
      <wf_collect>true</wf_collect>
      <disk_io>low</disk_io>
      <max_seconds>10000000</max_seconds>
      <nstep>1</nstep>
      <etot_conv_thr>5.000000000000000E-005</etot_conv_thr>
      <forc_conv_thr>5.000000000000000E-004</forc_conv_thr>
      <press_conv_thr>5.000000000000000E-001</press_conv_thr>
      <verbosity>low</verbosity>
      <print_every>100000</print_every>
      <fcp>false</fcp>
      <rism>false</rism>
    </control_variables>
    <atomic_species ntyp="1">
      <species name="C">
        <mass>1.201070000000000E+001</mass>
        <pseudo_file>C.pbe-n-kjpaw_psl.1.0.0.UPF</pseudo_file>
      </species>
    </atomic_species>
    <atomic_structure nat="2" alat="4.6940000000000000" bravais_index="4">
      <atomic_positions>
        <atom name="C" index="1">0.000000000000000E+000  0.000000000000000E+000  0.000000000000000E+000</atom>
        <atom name="C" index="2">0.000000000000000E+000  2.710082308200000E+000  0.000000000000000E+000</atom>
      </atomic_positions>
      <cell>
        <a1>4.694000000000000E+000  0.000000000000000E+000  0.000000000000000E+000</a1>
        <a2>-2.347000000000000E+000  4.065123245364443E+000  0.000000000000000E+000</a2>
        <a3>0.000000000000000E+000  0.000000000000000E+000  2.816400000000000E+001</a3>
      </cell>
    </atomic_structure>
    <dft>
      <functional>PBE</functional>
    </dft>
    <spin>
      <lsda>false</lsda>
      <noncolin>false</noncolin>
      <spinorbit>false</spinorbit>
    </spin>
    <bands>
      <smearing degauss="5.0000000000000001E-003">gaussian</smearing>
      <tot_charge>0.000000000000000E+000</tot_charge>
      <occupations>smearing</occupations>
    </bands>
    <basis>
      <gamma_only>false</gamma_only>
      <ecutwfc>4.000000000000000E+001</ecutwfc>
      <ecutrho>4.000000000000000E+002</ecutrho>
    </basis>
    <electron_control>
      <diagonalization>davidson</diagonalization>
      <mixing_mode>plain</mixing_mode>
      <mixing_beta>7.000000000000000E-001</mixing_beta>
      <conv_thr>5.000000000000000E-009</conv_thr>
      <mixing_ndim>8</mixing_ndim>
      <max_nstep>100</max_nstep>
      <exx_nstep>100</exx_nstep>
      <real_space_q>false</real_space_q>
      <real_space_beta>false</real_space_beta>
      <tq_smoothing>false</tq_smoothing>
      <tbeta_smoothing>false</tbeta_smoothing>
      <diago_thr_init>0.000000000000000E+000</diago_thr_init>
      <diago_full_acc>false</diago_full_acc>
      <diago_cg_maxiter>20</diago_cg_maxiter>
      <diago_ppcg_maxiter>20</diago_ppcg_maxiter>
      <diago_rmm_ndim>4</diago_rmm_ndim>
      <diago_gs_nblock>16</diago_gs_nblock>
      <diago_rmm_conv>false</diago_rmm_conv>
    </electron_control>
    <k_points_IBZ>
      <monkhorst_pack nk1="9" nk2="9" nk3="1" k1="0" k2="0" k3="0">Monkhorst-Pack</monkhorst_pack>
    </k_points_IBZ>
    <ion_control>
      <ion_dynamics>none</ion_dynamics>
      <upscale>1.000000000000000E+002</upscale>
      <remove_rigid_rot>false</remove_rigid_rot>
      <refold_pos>false</refold_pos>
    </ion_control>
    <cell_control>
      <cell_dynamics>none</cell_dynamics>
      <pressure>0.000000000000000E+000</pressure>
      <wmass>0.000000000000000E+000</wmass>
      <cell_do_free>all</cell_do_free>
    </cell_control>
    <symmetry_flags>
      <nosym>false</nosym>
      <nosym_evc>false</nosym_evc>
      <noinv>false</noinv>
      <no_t_rev>false</no_t_rev>
      <force_symmorphic>false</force_symmorphic>
      <use_all_frac>false</use_all_frac>
    </symmetry_flags>
    <free_positions rank="2" dims="           3           2">
           1           1           1
           1           1           1
    </free_positions>
    <twoch_>
      <twochem>false</twochem>
      <nbnd_cond>0</nbnd_cond>
      <degauss_cond>0.000000000000000E+000</degauss_cond>
      <nelec_cond>0.000000000000000E+000</nelec_cond>
    </twoch_>
  </input>
  <output>
    <convergence_info>
      <scf_conv>
        <convergence_achieved>true</convergence_achieved>
        <n_scf_steps>6</n_scf_steps>
        <scf_error>1.729602785503100E-010</scf_error>
      </scf_conv>
      <wf_collected>true</wf_collected>
    </convergence_info>
    <algorithmic_info>
      <real_space_q>false</real_space_q>
      <real_space_beta>false</real_space_beta>
      <uspp>true</uspp>
      <paw>true</paw>
    </algorithmic_info>
    <atomic_species ntyp="1" pseudo_dir="../../../../../pseudos/">
      <species name="C">
        <mass>1.201070000000000E+001</mass>
        <pseudo_file>C.pbe-n-kjpaw_psl.1.0.0.UPF</pseudo_file>
      </species>
    </atomic_species>
    <atomic_structure nat="2" num_of_atomic_wfc="8" alat="4.6940000000000000" bravais_index="4">
      <atomic_positions>
        <atom name="C" index="1">
  0.000000000000000E+000  0.000000000000000E+000  0.000000000000000E+000
        </atom>
        <atom name="C" index="2">0.000000000000000E+000  2.710082308200000E+000  0.000000000000000E+000</atom>
      </atomic_positions>
      <cell>
        <a1>4.694000000000000E+000  0.000000000000000E+000  0.000000000000000E+000</a1>
        <a2>-2.347000000000000E+000  4.065123245364443E+000  0.000000000000000E+000</a2>
        <a3>0.000000000000000E+000  0.000000000000000E+000  2.816400000000000E+001</a3>
      </cell>
    </atomic_structure>
    <symmetries>
      <nsym>24</nsym>
      <colin_mag>-1</colin_mag>
      <nrot>24</nrot>
      <space_group>0</space_group>
      <symmetry>
        <info name="identity">crystal_symmetry</info>
        <rotation rank="2" dims="           3           3">
  1.000000000000000E+000  0.000000000000000E+000  0.000000000000000E+000
  0.000000000000000E+000  1.000000000000000E+000  0.000000000000000E+000
  0.000000000000000E+000  0.000000000000000E+000  1.000000000000000E+000
        </rotation>
        <fractional_translation>
  0.000000000000000E+000  0.000000000000000E+000  0.000000000000000E+000
        </fractional_translation>
        <equivalent_atoms size="2" nat="2">
           1           2
        </equivalent_atoms>
      </symmetry>
      <symmetry>
        <info name="180 deg rotation - cart. axis [0,0,1]">crystal_symmetry</info>
        <rotation rank="2" dims="           3           3">
 -1.000000000000000E+000  0.000000000000000E+000  0.000000000000000E+000
  0.000000000000000E+000 -1.000000000000000E+000  0.000000000000000E+000
  0.000000000000000E+000  0.000000000000000E+000  1.000000000000000E+000
        </rotation>
        <fractional_translation>
 -3.333333511216875E-001  3.333332977566250E-001  0.000000000000000E+000
        </fractional_translation>
        <equivalent_atoms size="2" nat="2">
           2           1
        </equivalent_atoms>
      </symmetry>
      <symmetry>
        <info name="180 deg rotation - cart. axis [0,1,0]">crystal_symmetry</info>
        <rotation rank="2" dims="           3           3">
 -1.000000000000000E+000  1.000000000000000E+000  0.000000000000000E+000
  0.000000000000000E+000  1.000000000000000E+000  0.000000000000000E+000
  0.000000000000000E+000  0.000000000000000E+000 -1.000000000000000E+000
        </rotation>
        <fractional_translation>
  0.000000000000000E+000  0.000000000000000E+000  0.000000000000000E+000
        </fractional_translation>
        <equivalent_atoms size="2" nat="2">
           1           2
        </equivalent_atoms>
      </symmetry>
      <symmetry>
        <info name="180 deg rotation - cart. axis [1,0,0]">crystal_symmetry</info>
        <rotation rank="2" dims="           3           3">
  1.000000000000000E+000 -1.000000000000000E+000  0.000000000000000E+000
  0.000000000000000E+000 -1.000000000000000E+000  0.000000000000000E+000
  0.000000000000000E+000  0.000000000000000E+000 -1.000000000000000E+000
        </rotation>
        <fractional_translation>
 -3.333333511216875E-001  3.333332977566250E-001  0.000000000000000E+000
        </fractional_translation>
        <equivalent_atoms size="2" nat="2">
           2           1
        </equivalent_atoms>
      </symmetry>
      <symmetry>
        <info name=" 60 deg rotation - cryst. axis [0,0,1]">crystal_symmetry</info>
        <rotation rank="2" dims="           3           3">
  1.000000000000000E+000 -1.000000000000000E+000  0.000000000000000E+000
  1.000000000000000E+000  0.000000000000000E+000  0.000000000000000E+000
  0.000000000000000E+000  0.000000000000000E+000  1.000000000000000E+000
        </rotation>
        <fractional_translation>
 -3.333333511216875E-001  3.333333511216875E-001  0.000000000000000E+000
        </fractional_translation>
        <equivalent_atoms size="2" nat="2">
           2           1
        </equivalent_atoms>
      </symmetry>
      <symmetry>
        <info name=" 60 deg rotation - cryst. axis [0,0,-1]">crystal_symmetry</info>
        <rotation rank="2" dims="           3           3">
  0.000000000000000E+000  1.000000000000000E+000  0.000000000000000E+000
 -1.000000000000000E+000  1.000000000000000E+000  0.000000000000000E+000
  0.000000000000000E+000  0.000000000000000E+000  1.000000000000000E+000
        </rotation>
        <fractional_translation>
 -3.333332977566250E-001  3.333333511216875E-001  0.000000000000000E+000
        </fractional_translation>
        <equivalent_atoms size="2" nat="2">
           2           1
        </equivalent_atoms>
      </symmetry>
      <symmetry>
        <info name="120 deg rotation - cryst. axis [0,0,1]">crystal_symmetry</info>
        <rotation rank="2" dims="           3           3">
  0.000000000000000E+000 -1.000000000000000E+000  0.000000000000000E+000
  1.000000000000000E+000 -1.000000000000000E+000  0.000000000000000E+000
  0.000000000000000E+000  0.000000000000000E+000  1.000000000000000E+000
        </rotation>
        <fractional_translation>
  0.000000000000000E+000  0.000000000000000E+000  0.000000000000000E+000
        </fractional_translation>
        <equivalent_atoms size="2" nat="2">
           1           2
        </equivalent_atoms>
      </symmetry>
      <symmetry>
        <info name="120 deg rotation - cryst. axis [0,0,-1]">crystal_symmetry</info>
        <rotation rank="2" dims="           3           3">
 -1.000000000000000E+000  1.000000000000000E+000  0.000000000000000E+000
 -1.000000000000000E+000  0.000000000000000E+000  0.000000000000000E+000
  0.000000000000000E+000  0.000000000000000E+000  1.000000000000000E+000
        </rotation>
        <fractional_translation>
  0.000000000000000E+000  0.000000000000000E+000  0.000000000000000E+000
        </fractional_translation>
        <equivalent_atoms size="2" nat="2">
           1           2
        </equivalent_atoms>
      </symmetry>
      <symmetry>
        <info name="180 deg rotation - cryst. axis [1,-1,0]">crystal_symmetry</info>
        <rotation rank="2" dims="           3           3">
  0.000000000000000E+000 -1.000000000000000E+000  0.000000000000000E+000
 -1.000000000000000E+000  0.000000000000000E+000  0.000000000000000E+000
  0.000000000000000E+000  0.000000000000000E+000 -1.000000000000000E+000
        </rotation>
        <fractional_translation>
  0.000000000000000E+000  0.000000000000000E+000  0.000000000000000E+000
        </fractional_translation>
        <equivalent_atoms size="2" nat="2">
           1           2
        </equivalent_atoms>
      </symmetry>
      <symmetry>
        <info name="180 deg rotation - cryst. axis [2,1,0]">crystal_symmetry</info>
        <rotation rank="2" dims="           3           3">
  1.000000000000000E+000  0.000000000000000E+000  0.000000000000000E+000
  1.000000000000000E+000 -1.000000000000000E+000  0.000000000000000E+000
  0.000000000000000E+000  0.000000000000000E+000 -1.000000000000000E+000
        </rotation>
        <fractional_translation>
  0.000000000000000E+000  0.000000000000000E+000  0.000000000000000E+000
        </fractional_translation>
        <equivalent_atoms size="2" nat="2">
           1           2
        </equivalent_atoms>
      </symmetry>
      <symmetry>
        <info name="180 deg rotation - cryst. axis [0,1,0]">crystal_symmetry</info>
        <rotation rank="2" dims="           3           3">
 -1.000000000000000E+000  0.000000000000000E+000  0.000000000000000E+000
 -1.000000000000000E+000  1.000000000000000E+000  0.000000000000000E+000
  0.000000000000000E+000  0.000000000000000E+000 -1.000000000000000E+000
        </rotation>
        <fractional_translation>
 -3.333333511216875E-001  3.333333511216875E-001  0.000000000000000E+000
        </fractional_translation>
        <equivalent_atoms size="2" nat="2">
           2           1
        </equivalent_atoms>
      </symmetry>
      <symmetry>
        <info name="180 deg rotation - cryst. axis [1,1,0]">crystal_symmetry</info>
        <rotation rank="2" dims="           3           3">
  0.000000000000000E+000  1.000000000000000E+000  0.000000000000000E+000
  1.000000000000000E+000  0.000000000000000E+000  0.000000000000000E+000
  0.000000000000000E+000  0.000000000000000E+000 -1.000000000000000E+000
        </rotation>
        <fractional_translation>
 -3.333332977566250E-001  3.333333511216875E-001  0.000000000000000E+000
        </fractional_translation>
        <equivalent_atoms size="2" nat="2">
           2           1
        </equivalent_atoms>
      </symmetry>
      <symmetry>
        <info name="inversion">crystal_symmetry</info>
        <rotation rank="2" dims="           3           3">
 -1.000000000000000E+000  0.000000000000000E+000  0.000000000000000E+000
  0.000000000000000E+000 -1.000000000000000E+000  0.000000000000000E+000
  0.000000000000000E+000  0.000000000000000E+000 -1.000000000000000E+000
        </rotation>
        <fractional_translation>
 -3.333333511216875E-001  3.333332977566250E-001  0.000000000000000E+000
        </fractional_translation>
        <equivalent_atoms size="2" nat="2">
           2           1
        </equivalent_atoms>
      </symmetry>
      <symmetry>
        <info name="inv. 180 deg rotation - cart. axis [0,0,1]">crystal_symmetry</info>
        <rotation rank="2" dims="           3           3">
  1.000000000000000E+000  0.000000000000000E+000  0.000000000000000E+000
  0.000000000000000E+000  1.000000000000000E+000  0.000000000000000E+000
  0.000000000000000E+000  0.000000000000000E+000 -1.000000000000000E+000
        </rotation>
        <fractional_translation>
  0.000000000000000E+000  0.000000000000000E+000  0.000000000000000E+000
        </fractional_translation>
        <equivalent_atoms size="2" nat="2">
           1           2
        </equivalent_atoms>
      </symmetry>
      <symmetry>
        <info name="inv. 180 deg rotation - cart. axis [0,1,0]">crystal_symmetry</info>
        <rotation rank="2" dims="           3           3">
  1.000000000000000E+000 -1.000000000000000E+000  0.000000000000000E+000
  0.000000000000000E+000 -1.000000000000000E+000  0.000000000000000E+000
  0.000000000000000E+000  0.000000000000000E+000  1.000000000000000E+000
        </rotation>
        <fractional_translation>
 -3.333333511216875E-001  3.333332977566250E-001  0.000000000000000E+000
        </fractional_translation>
        <equivalent_atoms size="2" nat="2">
           2           1
        </equivalent_atoms>
      </symmetry>
      <symmetry>
        <info name="inv. 180 deg rotation - cart. axis [1,0,0]">crystal_symmetry</info>
        <rotation rank="2" dims="           3           3">
 -1.000000000000000E+000  1.000000000000000E+000  0.000000000000000E+000
  0.000000000000000E+000  1.000000000000000E+000  0.000000000000000E+000
  0.000000000000000E+000  0.000000000000000E+000  1.000000000000000E+000
        </rotation>
        <fractional_translation>
  0.000000000000000E+000  0.000000000000000E+000  0.000000000000000E+000
        </fractional_translation>
        <equivalent_atoms size="2" nat="2">
           1           2
        </equivalent_atoms>
      </symmetry>
      <symmetry>
        <info name="inv.  60 deg rotation - cryst. axis [0,0,1]">crystal_symmetry</info>
        <rotation rank="2" dims="           3           3">
 -1.000000000000000E+000  1.000000000000000E+000  0.000000000000000E+000
 -1.000000000000000E+000  0.000000000000000E+000  0.000000000000000E+000
  0.000000000000000E+000  0.000000000000000E+000 -1.000000000000000E+000
        </rotation>
        <fractional_translation>
  0.000000000000000E+000  0.000000000000000E+000  0.000000000000000E+000
        </fractional_translation>
        <equivalent_atoms size="2" nat="2">
           1           2
        </equivalent_atoms>
      </symmetry>
      <symmetry>
        <info name="inv.  60 deg rotation - cryst. axis [0,0,-1]">crystal_symmetry</info>
        <rotation rank="2" dims="           3           3">
  0.000000000000000E+000 -1.000000000000000E+000  0.000000000000000E+000
  1.000000000000000E+000 -1.000000000000000E+000  0.000000000000000E+000
  0.000000000000000E+000  0.000000000000000E+000 -1.000000000000000E+000
        </rotation>
        <fractional_translation>
  0.000000000000000E+000  0.000000000000000E+000  0.000000000000000E+000
        </fractional_translation>
        <equivalent_atoms size="2" nat="2">
           1           2
        </equivalent_atoms>
      </symmetry>
      <symmetry>
        <info name="inv. 120 deg rotation - cryst. axis [0,0,1]">crystal_symmetry</info>
        <rotation rank="2" dims="           3           3">
  0.000000000000000E+000  1.000000000000000E+000  0.000000000000000E+000
 -1.000000000000000E+000  1.000000000000000E+000  0.000000000000000E+000
  0.000000000000000E+000  0.000000000000000E+000 -1.000000000000000E+000
        </rotation>
        <fractional_translation>
 -3.333332977566250E-001  3.333333511216875E-001  0.000000000000000E+000
        </fractional_translation>
        <equivalent_atoms size="2" nat="2">
           2           1
        </equivalent_atoms>
      </symmetry>
      <symmetry>
        <info name="inv. 120 deg rotation - cryst. axis [0,0,-1]">crystal_symmetry</info>
        <rotation rank="2" dims="           3           3">
  1.000000000000000E+000 -1.000000000000000E+000  0.000000000000000E+000
  1.000000000000000E+000  0.000000000000000E+000  0.000000000000000E+000
  0.000000000000000E+000  0.000000000000000E+000 -1.000000000000000E+000
        </rotation>
        <fractional_translation>
 -3.333333511216875E-001  3.333333511216875E-001  0.000000000000000E+000
        </fractional_translation>
        <equivalent_atoms size="2" nat="2">
           2           1
        </equivalent_atoms>
      </symmetry>
      <symmetry>
        <info name="inv. 180 deg rotation - cryst. axis [1,-1,0]">crystal_symmetry</info>
        <rotation rank="2" dims="           3           3">
  0.000000000000000E+000  1.000000000000000E+000  0.000000000000000E+000
  1.000000000000000E+000  0.000000000000000E+000  0.000000000000000E+000
  0.000000000000000E+000  0.000000000000000E+000  1.000000000000000E+000
        </rotation>
        <fractional_translation>
 -3.333332977566250E-001  3.333333511216875E-001  0.000000000000000E+000
        </fractional_translation>
        <equivalent_atoms size="2" nat="2">
           2           1
        </equivalent_atoms>
      </symmetry>
      <symmetry>
        <info name="inv. 180 deg rotation - cryst. axis [2,1,0]">crystal_symmetry</info>
        <rotation rank="2" dims="           3           3">
 -1.000000000000000E+000  0.000000000000000E+000  0.000000000000000E+000
 -1.000000000000000E+000  1.000000000000000E+000  0.000000000000000E+000
  0.000000000000000E+000  0.000000000000000E+000  1.000000000000000E+000
        </rotation>
        <fractional_translation>
 -3.333333511216875E-001  3.333333511216875E-001  0.000000000000000E+000
        </fractional_translation>
        <equivalent_atoms size="2" nat="2">
           2           1
        </equivalent_atoms>
      </symmetry>
      <symmetry>
        <info name="inv. 180 deg rotation - cryst. axis [0,1,0]">crystal_symmetry</info>
        <rotation rank="2" dims="           3           3">
  1.000000000000000E+000  0.000000000000000E+000  0.000000000000000E+000
  1.000000000000000E+000 -1.000000000000000E+000  0.000000000000000E+000
  0.000000000000000E+000  0.000000000000000E+000  1.000000000000000E+000
        </rotation>
        <fractional_translation>
  0.000000000000000E+000  0.000000000000000E+000  0.000000000000000E+000
        </fractional_translation>
        <equivalent_atoms size="2" nat="2">
           1           2
        </equivalent_atoms>
      </symmetry>
      <symmetry>
        <info name="inv. 180 deg rotation - cryst. axis [1,1,0]">crystal_symmetry</info>
        <rotation rank="2" dims="           3           3">
  0.000000000000000E+000 -1.000000000000000E+000  0.000000000000000E+000
 -1.000000000000000E+000  0.000000000000000E+000  0.000000000000000E+000
  0.000000000000000E+000  0.000000000000000E+000  1.000000000000000E+000
        </rotation>
        <fractional_translation>
  0.000000000000000E+000  0.000000000000000E+000  0.000000000000000E+000
        </fractional_translation>
        <equivalent_atoms size="2" nat="2">
           1           2
        </equivalent_atoms>
      </symmetry>
    </symmetries>
    <basis_set>
      <gamma_only>false</gamma_only>
      <ecutwfc>4.000000000000000E+001</ecutwfc>
      <ecutrho>4.000000000000000E+002</ecutrho>
      <fft_grid nr1="45" nr2="45" nr3="256"></fft_grid>
      <fft_smooth nr1="27" nr2="27" nr3="162"></fft_smooth>
      <fft_box nr1="45" nr2="45" nr3="256"></fft_box>
      <ngm>205237</ngm>
      <ngms>52103</ngms>
      <npwx>6549</npwx>
      <reciprocal_lattice>
        <b1>
  1.000000000000000E+000  5.773502691895848E-001 -0.000000000000000E+000
        </b1>
        <b2>0.000000000000000E+000  1.154700538379170E+000  0.000000000000000E+000</b2>
        <b3>0.000000000000000E+000 -0.000000000000000E+000  1.666666666666667E-001</b3>
      </reciprocal_lattice>
    </basis_set>
    <dft>
      <functional>PBE</functional>
    </dft>
    <magnetization>
      <lsda>false</lsda>
      <noncolin>false</noncolin>
      <spinorbit>false</spinorbit>
      <absolute>0.000000000000000E+000</absolute>
    </magnetization>
    <total_energy>
      <etot>-1.844331565660215E+001</etot>
      <eband>-3.191649984422405E+000</eband>
      <ehart>3.910055717333205E+001</ehart>
      <vtxc>-4.648891487304285E+000</vtxc>
      <etxc>-4.620825172760033E+000</etxc>
      <ewald>2.984150849692990E+001</ewald>
      <demet>-1.393060700075874E-004</demet>
    </total_energy>
    <band_structure>
      <lsda>false</lsda>
      <noncolin>false</noncolin>
      <spinorbit>false</spinorbit>
      <nbnd>8</nbnd>
      <nelec>8.000000000000000E+000</nelec>
      <fermi_energy>-6.564349412157254E-002</fermi_energy>
      <starting_k_points>
        <monkhorst_pack nk1="9" nk2="9" nk3="1" k1="0" k2="0" k3="0">Monkhorst-Pack</monkhorst_pack>
      </starting_k_points>
      <nks>12</nks>
      <occupations_kind>smearing</occupations_kind>
      <smearing degauss="5.0000000000000001E-003">gaussian</smearing>
      <ks_energies>
        <k_point weight="2.4691358024691360E-002">0.000000000000000E+000  0.000000000000000E+000  0.000000000000000E+000</k_point>
        <npw>6549</npw>
        <eigenvalues size="8">
 -7.769239499083360E-001 -3.404511447277079E-001 -1.781922676360382E-001
 -1.781921518463050E-001  5.489253913370359E-002
  8.713745943115719E-002  1.010517882196126E-001  1.726836221885731E-001
        </eigenvalues>
        <occupations size="8">
  1.000000000000000E+000  1.000000000000000E+000  1.000000000000000E+000
  1.000000000000000E+000  0.000000000000000E+000
  0.000000000000000E+000  0.000000000000000E+000  0.000000000000000E+000
        </occupations>
      </ks_energies>
      <ks_energies>
        <k_point weight="0.14814814814814817">
  0.000000000000000E+000  1.283000598199077E-001  0.000000000000000E+000
        </k_point>
        <npw>6531</npw>
        <eigenvalues size="8">
 -7.663616062632528E-001 -3.278939145389644E-001 -2.188398866968621E-001
 -1.987398765619868E-001  6.927276339156054E-002
  1.016122240688943E-001  1.156491143287421E-001  1.870240021050955E-001
        </eigenvalues>
        <occupations size="8">
  1.000000000000000E+000  1.000000000000000E+000  1.000000000000000E+000
  1.000000000000000E+000  0.000000000000000E+000
  0.000000000000000E+000  0.000000000000000E+000  0.000000000000000E+000
        </occupations>
      </ks_energies>
      <ks_energies>
        <k_point weight="0.14814814814814817">
  0.000000000000000E+000  2.566001196398154E-001  0.000000000000000E+000
        </k_point>
        <npw>6502</npw>
        <eigenvalues size="8">
 -7.348881540062785E-001 -3.115260319146217E-001 -2.908805503712981E-001
 -2.402702954336499E-001  1.123651418796161E-001
  1.447448773512326E-001  1.594154419038372E-001  2.204107042484689E-001
        </eigenvalues>
        <occupations size="8">
  1.000000000000000E+000  1.000000000000000E+000  1.000000000000000E+000
  1.000000000000000E+000  0.000000000000000E+000
  0.000000000000000E+000  0.000000000000000E+000  0.000000000000000E+000
        </occupations>
      </ks_energies>
      <ks_energies>
        <k_point weight="0.14814814814814817">
  0.000000000000000E+000  3.849001794597232E-001  0.000000000000000E+000
        </k_point>
        <npw>6478</npw>
        <eigenvalues size="8">
 -6.832902763742108E-001 -4.178511808508157E-001 -2.770113929995782E-001
 -2.323537674864176E-001  1.116102707959141E-001
  1.835475240756606E-001  2.106245748555842E-001  2.176275586189440E-001
        </eigenvalues>
        <occupations size="8">
  1.000000000000000E+000  1.000000000000000E+000  1.000000000000000E+000
  1.000000000000000E+000  0.000000000000000E+000
  0.000000000000000E+000  0.000000000000000E+000  0.000000000000000E+000
        </occupations>
      </ks_energies>
      <ks_energies>
        <k_point weight="0.14814814814814817">
  0.000000000000000E+000  5.132002392796309E-001  0.000000000000000E+000
        </k_point>
        <npw>6468</npw>
        <eigenvalues size="8">
 -6.145966341875514E-001 -5.170405684007878E-001 -2.973233400167608E-001
 -1.661137216867250E-001  1.498697750328046E-002
  1.993284112949270E-001  2.835681766804483E-001  3.167992236780232E-001
        </eigenvalues>
        <occupations size="8">
  1.000000000000000E+000  1.000000000000000E+000  1.000000000000000E+000
  1.000000000000000E+000  0.000000000000000E+000
  0.000000000000000E+000  0.000000000000000E+000  0.000000000000000E+000
        </occupations>
      </ks_energies>
      <ks_energies>
        <k_point weight="0.14814814814814817">
  1.111111111111111E-001  1.924500897298616E-001  0.000000000000000E+000
        </k_point>
        <npw>6531</npw>
        <eigenvalues size="8">
 -7.453440707548800E-001 -3.030818103355387E-001 -2.756187726449377E-001
 -2.398623593103641E-001  9.803421281818309E-002
  1.304859779191294E-001  1.448524288707597E-001  2.503870584570090E-001
        </eigenvalues>
        <occupations size="8">
  1.000000000000000E+000  1.000000000000000E+000  1.000000000000000E+000
  1.000000000000000E+000  0.000000000000000E+000
  0.000000000000000E+000  0.000000000000000E+000  0.000000000000000E+000
        </occupations>
      </ks_energies>
      <ks_energies>
        <k_point weight="0.29629629629629634">
  1.111111111111111E-001  3.207501495497693E-001  0.000000000000000E+000
        </k_point>
        <npw>6466</npw>
        <eigenvalues size="8">
 -7.037973876041993E-001 -3.646015002257380E-001 -2.897918808911492E-001
 -2.549558526663558E-001  1.553957896648723E-001
  1.563069058969553E-001  1.883825007546172E-001  2.032027033489267E-001
        </eigenvalues>
        <occupations size="8">
  1.000000000000000E+000  1.000000000000000E+000  1.000000000000000E+000
  1.000000000000000E+000  0.000000000000000E+000
  0.000000000000000E+000  0.000000000000000E+000  0.000000000000000E+000
        </occupations>
      </ks_energies>
      <ks_energies>
        <k_point weight="0.29629629629629634">
  1.111111111111111E-001  4.490502093696770E-001  0.000000000000000E+000
        </k_point>
        <npw>6494</npw>
        <eigenvalues size="8">
 -6.431716277867146E-001 -4.645318772391319E-001 -3.216628336222820E-001
 -1.891964524435256E-001  5.438558098686901E-002
  2.395906355979624E-001  2.499670831620340E-001  2.730641381941868E-001
        </eigenvalues>
        <occupations size="8">
  1.000000000000000E+000  1.000000000000000E+000  1.000000000000000E+000
  1.000000000000000E+000  0.000000000000000E+000
  0.000000000000000E+000  0.000000000000000E+000  0.000000000000000E+000
        </occupations>
      </ks_energies>
      <ks_energies>
        <k_point weight="0.14814814814814817">
  1.111111111111111E-001  5.773502691895848E-001  0.000000000000000E+000
        </k_point>
        <npw>6480</npw>
        <eigenvalues size="8">
 -5.811596054782895E-001 -5.410747875928646E-001 -3.325151775197920E-001
 -1.412751479667841E-001 -7.320168032600016E-003
  2.428717075285720E-001  3.491879101050505E-001  3.552896007208571E-001
        </eigenvalues>
        <occupations size="8">
  1.000000000000000E+000  1.000000000000000E+000  1.000000000000000E+000
  1.000000000000000E+000  1.949471154837328E-061
  0.000000000000000E+000  0.000000000000000E+000  0.000000000000000E+000
        </occupations>
      </ks_energies>
      <ks_energies>
        <k_point weight="0.14814814814814817">
  2.222222222222222E-001  3.849001794597232E-001  0.000000000000000E+000
        </k_point>
        <npw>6487</npw>
        <eigenvalues size="8">
 -6.531004835120637E-001 -4.202185851665194E-001 -3.621402663031341E-001
 -1.980069909939220E-001  7.657037580758080E-002
  2.266272666483017E-001  2.571436264239353E-001  2.760819281662611E-001
        </eigenvalues>
        <occupations size="8">
  1.000000000000000E+000  1.000000000000000E+000  1.000000000000000E+000
  1.000000000000000E+000  0.000000000000000E+000
  0.000000000000000E+000  0.000000000000000E+000  0.000000000000000E+000
        </occupations>
      </ks_energies>
      <ks_energies>
        <k_point weight="0.29629629629629634">
  2.222222222222222E-001  5.132002392796309E-001  0.000000000000000E+000
        </k_point>
        <npw>6495</npw>
        <eigenvalues size="8">
 -5.863805136281832E-001 -4.964118676152434E-001 -3.985099007655732E-001
 -1.305644729232093E-001 -3.827777670673719E-003
  3.234514348907841E-001  3.320629661191466E-001  3.475874319735492E-001
        </eigenvalues>
        <occupations size="8">
  1.000000000000000E+000  1.000000000000000E+000  1.000000000000000E+000
  1.000000000000000E+000  9.464828267457953E-069
  0.000000000000000E+000  0.000000000000000E+000  0.000000000000000E+000
        </occupations>
      </ks_energies>
      <ks_energies>
        <k_point weight="4.9382716049382720E-002">
  3.333333333333333E-001  5.773502691895848E-001  0.000000000000000E+000
        </k_point>
        <npw>6495</npw>
        <eigenvalues size="8">
 -5.267067637899436E-001 -5.267066938089153E-001 -4.483807052300059E-001
 -6.564352158778031E-002 -6.564346665150586E-002
  3.233290667138764E-001  4.019105327944250E-001  4.019107968653050E-001
        </eigenvalues>
        <occupations size="8">
  1.000000000000000E+000  1.000000000000000E+000  1.000000000000000E+000
  5.000030992296642E-001  4.999969003349040E-001
  0.000000000000000E+000  0.000000000000000E+000  0.000000000000000E+000
        </occupations>
      </ks_energies>
    </band_structure>
  </output>
  <exit_status>0</exit_status>
  <timing_info>
    <total label="PWSCF">
      <cpu>2.979750000000000E+001</cpu>
      <wall>3.092139816284180E+001</wall>
    </total>
    <partial label="init_run" calls="1">
      <cpu>3.271950000000000E+000</cpu>
      <wall>5.777477025985718E+000</wall>
    </partial>
    <partial label="hinit0" calls="1">
      <cpu>1.059964000000000E+000</cpu>
      <wall>2.358019113540649E+000</wall>
    </partial>
    <partial label="init_vloc" calls="1">
      <cpu>5.708599999999997E-002</cpu>
      <wall>2.503910064697266E-001</wall>
    </partial>
    <partial label="init_us_1" calls="1">
      <cpu>2.018180000000000E-001</cpu>
      <wall>3.664009571075439E-001</wall>
    </partial>
    <partial label="fft" calls="89">
      <cpu>1.547971999999998E+000</cpu>
      <wall>2.338580131530762E+000</wall>
    </partial>
    <partial label="potinit" calls="1">
      <cpu>8.156979999999998E-001</cpu>
      <wall>9.078640937805176E-001</wall>
    </partial>
    <partial label="PAW_symme" calls="13">
      <cpu>6.379999999985841E-004</cpu>
      <wall>6.968975067138672E-004</wall>
    </partial>
    <partial label="v_of_rho" calls="7">
      <cpu>1.804017000000002E+000</cpu>
      <wall>2.239902257919312E+000</wall>
    </partial>
    <partial label="v_xc" calls="7">
      <cpu>1.698359999999997E+000</cpu>
      <wall>2.071730136871338E+000</wall>
    </partial>
    <partial label="v_h" calls="7">
      <cpu>1.056309999999989E-001</cpu>
      <wall>1.681227684020996E-001</wall>
    </partial>
    <partial label="PAW_pot" calls="7">
      <cpu>7.175789999999971E-001</cpu>
      <wall>8.704607486724854E-001</wall>
    </partial>
    <partial label="interpolate" calls="7">
      <cpu>3.442400000000028E-001</cpu>
      <wall>3.497872352600098E-001</wall>
    </partial>
    <partial label="ffts" calls="13">
      <cpu>2.572499999999991E-001</cpu>
      <wall>2.622387409210205E-001</wall>
    </partial>
    <partial label="newd" calls="7">
      <cpu>9.902500000000032E-001</cpu>
      <wall>1.760443210601807E+000</wall>
    </partial>
    <partial label="wfcinit" calls="1">
      <cpu>1.107432000000000E+000</cpu>
      <wall>1.800251007080078E+000</wall>
    </partial>
    <partial label="init_us_2" calls="156">
      <cpu>3.525210000000030E-001</cpu>
      <wall>2.550380229949951E-001</wall>
    </partial>
    <partial label="wfcinit:atom" calls="12">
      <cpu>1.766899999999971E-002</cpu>
      <wall>1.273775100708008E-002</wall>
    </partial>
    <partial label="atomic_wfc" calls="12">
      <cpu>1.760000000000028E-002</cpu>
      <wall>1.270532608032227E-002</wall>
    </partial>
    <partial label="wfcinit:wfcr" calls="12">
      <cpu>1.009791999999999E+000</cpu>
      <wall>1.703726053237915E+000</wall>
    </partial>
    <partial label="wfcrot" calls="12">
      <cpu>1.009745000000001E+000</cpu>
      <wall>1.703688859939575E+000</wall>
    </partial>
    <partial label="rotwfck" calls="12">
      <cpu>1.009660000000000E+000</cpu>
      <wall>1.703631639480591E+000</wall>
    </partial>
    <partial label="rotwfck:hpsi" calls="12">
      <cpu>9.838620000000011E-001</cpu>
      <wall>1.658530950546265E+000</wall>
    </partial>
    <partial label="h_psi_bgrp" calls="413">
      <cpu>1.838543000000004E+001</cpu>
      <wall>1.760274505615234E+001</wall>
    </partial>
    <partial label="h_psi" calls="413">
      <cpu>1.837971300000007E+001</cpu>
      <wall>1.760148072242737E+001</wall>
    </partial>
    <partial label="h_psi:pot" calls="413">
      <cpu>1.831908600000003E+001</cpu>
      <wall>1.756359529495239E+001</wall>
    </partial>
    <partial label="vloc_psi" calls="413">
      <cpu>1.673589299999998E+001</cpu>
      <wall>1.453685283660889E+001</wall>
    </partial>
    <partial label="fftw" calls="4412">
      <cpu>1.273900099999993E+001</cpu>
      <wall>1.112153816223145E+001</wall>
    </partial>
    <partial label="h_psi:calbec" calls="413">
      <cpu>3.442489999999978E-001</cpu>
      <wall>4.679346084594727E-001</wall>
    </partial>
    <partial label="calbec" calls="485">
      <cpu>3.789310000000015E-001</cpu>
      <wall>4.966466426849365E-001</wall>
    </partial>
    <partial label="add_vuspsi" calls="413">
      <cpu>1.233856000000007E+000</cpu>
      <wall>2.555958032608032E+000</wall>
    </partial>
    <partial label="rotwfck:hc" calls="12">
      <cpu>1.735299999999995E-002</cpu>
      <wall>2.664351463317871E-002</wall>
    </partial>
    <partial label="s_psi_bgrp" calls="413">
      <cpu>3.249259999999872E-001</cpu>
      <wall>3.457500934600830E-001</wall>
    </partial>
    <partial label="s_psi" calls="413">
      <cpu>2.782789999999657E-001</cpu>
      <wall>3.218913078308105E-001</wall>
    </partial>
    <partial label="rotwfck:diag" calls="12">
      <cpu>2.337999999999951E-003</cpu>
      <wall>1.126766204833984E-003</wall>
    </partial>
    <partial label="cdiaghg" calls="401">
      <cpu>1.248750000000101E-001</cpu>
      <wall>6.554746627807617E-002</wall>
    </partial>
    <partial label="rotwfck:evc" calls="12">
      <cpu>5.972999999999562E-003</cpu>
      <wall>1.723957061767578E-002</wall>
    </partial>
    <partial label="electrons" calls="1">
      <cpu>2.638542500000000E+001</cpu>
      <wall>2.481159400939941E+001</wall>
    </partial>
    <partial label="c_bands" calls="6">
      <cpu>1.985464300000000E+001</cpu>
      <wall>1.779306507110596E+001</wall>
    </partial>
    <partial label="cegterg" calls="72">
      <cpu>1.929448599999996E+001</cpu>
      <wall>1.740710759162903E+001</wall>
    </partial>
    <partial label="cegterg:init" calls="72">
      <cpu>7.415900000000875E-002</cpu>
      <wall>3.661608695983887E-002</wall>
    </partial>
    <partial label="cegterg:upda" calls="329">
      <cpu>3.408079999999920E-001</cpu>
      <wall>3.025600910186768E-001</wall>
    </partial>
    <partial label="g_psi" calls="329">
      <cpu>8.839899999999190E-002</cpu>
      <wall>4.482650756835938E-002</wall>
    </partial>
    <partial label="cegterg:over" calls="329">
      <cpu>3.463329999999907E-001</cpu>
      <wall>1.883893013000488E-001</wall>
    </partial>
    <partial label="cegterg:diag" calls="389">
      <cpu>1.261090000000138E-001</cpu>
      <wall>6.573605537414551E-002</wall>
    </partial>
    <partial label="cegterg:last" calls="194">
      <cpu>4.405400000000235E-001</cpu>
      <wall>3.343634605407715E-001</wall>
    </partial>
    <partial label="sum_band" calls="6">
      <cpu>3.312729000000001E+000</cpu>
      <wall>2.461474895477295E+000</wall>
    </partial>
    <partial label="sum_band:wei" calls="6">
      <cpu>7.220000000032201E-004</cpu>
      <wall>3.719329833984375E-004</wall>
    </partial>
    <partial label="sum_band:loo" calls="6">
      <cpu>1.557438000000001E+000</cpu>
      <wall>1.151898145675659E+000</wall>
    </partial>
    <partial label="sum_band:buf" calls="72">
      <cpu>1.180400000000503E-002</cpu>
      <wall>8.392333984375000E-003</wall>
    </partial>
    <partial label="sum_band:ini" calls="72">
      <cpu>1.363600000000140E-001</cpu>
      <wall>1.048548221588135E-001</wall>
    </partial>
    <partial label="sum_band:cal" calls="72">
      <cpu>3.798800000000924E-002</cpu>
      <wall>3.040266036987305E-002</wall>
    </partial>
    <partial label="sum_band:bec" calls="72">
      <cpu>1.025000000005605E-003</cpu>
      <wall>7.684230804443359E-004</wall>
    </partial>
    <partial label="addusdens" calls="6">
      <cpu>1.550435000000000E+000</cpu>
      <wall>1.098774433135986E+000</wall>
    </partial>
    <partial label="addusd:skk" calls="6">
      <cpu>1.315700000000319E-002</cpu>
      <wall>1.382112503051758E-002</wall>
    </partial>
    <partial label="sum_band:sym" calls="6">
      <cpu>1.825549999999971E-001</cpu>
      <wall>1.896820068359375E-001</wall>
    </partial>
    <partial label="mix_rho" calls="6">
      <cpu>1.514610000000047E-001</cpu>
      <wall>1.584849357604980E-001</wall>
    </partial>
    <partial label="high_freq_mi" calls="5">
      <cpu>6.538199999999605E-002</cpu>
      <wall>6.678199768066406E-002</wall>
    </partial>
    <partial label="ions" calls="1">
      <cpu>2.000000002055913E-006</cpu>
      <wall>2.145767211914062E-006</wall>
    </partial>
  </timing_info>
  <closed DATE=" 9 Sep 2025" TIME=" 8:36:31"></closed>
</qes:espresso>
